odoo10_addon_business_requirement_deliverable_cost-10.0.1.0.0-py2.7-nspkg.pth
odoo/addons/business_requirement_deliverable_cost/README.rst
odoo/addons/business_requirement_deliverable_cost/__init__.py
odoo/addons/business_requirement_deliverable_cost/__manifest__.py
odoo/addons/business_requirement_deliverable_cost/data/business_data.xml
odoo/addons/business_requirement_deliverable_cost/data/business_requirement_deliverable_cost_demo.xml
odoo/addons/business_requirement_deliverable_cost/i18n/sl.po
odoo/addons/business_requirement_deliverable_cost/models/__init__.py
odoo/addons/business_requirement_deliverable_cost/models/business.py
odoo/addons/business_requirement_deliverable_cost/report/__init__.py
odoo/addons/business_requirement_deliverable_cost/report/br_deliverable_cost_report.py
odoo/addons/business_requirement_deliverable_cost/report/br_deliverable_cost_report_view.xml
odoo/addons/business_requirement_deliverable_cost/report/report.xml
odoo/addons/business_requirement_deliverable_cost/security/business_requirement_deliverable_security.xml
odoo/addons/business_requirement_deliverable_cost/security/ir.model.access.csv
odoo/addons/business_requirement_deliverable_cost/static/description/icon.png
odoo/addons/business_requirement_deliverable_cost/static/img/bus_req_acl1.png
odoo/addons/business_requirement_deliverable_cost/static/img/bus_req_acl2.png
odoo/addons/business_requirement_deliverable_cost/static/img/bus_req_acl3.png
odoo/addons/business_requirement_deliverable_cost/static/img/bus_req_control.png
odoo/addons/business_requirement_deliverable_cost/tests/__init__.py
odoo/addons/business_requirement_deliverable_cost/tests/test_br.py
odoo/addons/business_requirement_deliverable_cost/views/business.xml
odoo/addons/business_requirement_deliverable_cost/views/report_business_requirement_other_resources_report.xml
odoo10_addon_business_requirement_deliverable_cost-10.0.1.0.0.dist-info/DESCRIPTION.rst
odoo10_addon_business_requirement_deliverable_cost-10.0.1.0.0.dist-info/METADATA
odoo10_addon_business_requirement_deliverable_cost-10.0.1.0.0.dist-info/RECORD
odoo10_addon_business_requirement_deliverable_cost-10.0.1.0.0.dist-info/WHEEL
odoo10_addon_business_requirement_deliverable_cost-10.0.1.0.0.dist-info/metadata.json
odoo10_addon_business_requirement_deliverable_cost-10.0.1.0.0.dist-info/namespace_packages.txt
odoo10_addon_business_requirement_deliverable_cost-10.0.1.0.0.dist-info/top_level.txt
